{
    "version": "1.0",
    "name": "SceneA",
    "camera": {
        "scene_x": 0.0,
        "scene_y": 0.0,
        "scene_zoom": 1.0,
        "game_x": 0.0,
        "game_y": 0.0,
        "game_zoom": 1.0
    },
    "objects": [
        {
            "id": "6307fe70",
            "name": "anim_sprite",
            "sprite_path": "",
            "sprite_shape": "rectangle",
            "sprite_color": [
                255,
                255,
                255
            ],
            "transform": {
                "x": 650.0,
                "y": 300.0,
                "rotation": 0.0,
                "scale_x": 1.0,
                "scale_y": 1.0
            },
            "z_index": 0,
            "screen_space": false,
            "active": true,
            "locked": false,
            "physics_type": "none",
            "physics_mass": 1.0,
            "physics_friction": 0.98,
            "physics_bounce": 0.5,
            "physics_collision_category": null,
            "physics_collision_mask": null,
            "custom_data": {
                "width": 40,
                "height": 40
            }
        },
        {
            "id": "caaa1702",
            "name": "mover",
            "sprite_path": "",
            "sprite_shape": "rectangle",
            "sprite_color": [
                160,
                210,
                255
            ],
            "transform": {
                "x": 150.0,
                "y": 300.0,
                "rotation": 0.0,
                "scale_x": 1.0,
                "scale_y": 1.0
            },
            "z_index": 0,
            "screen_space": false,
            "active": true,
            "locked": false,
            "physics_type": "none",
            "physics_mass": 1.0,
            "physics_friction": 0.98,
            "physics_bounce": 0.5,
            "physics_collision_category": null,
            "physics_collision_mask": null,
            "custom_data": {
                "width": 60,
                "height": 60
            }
        },
        {
            "id": "ef30c6fd",
            "name": "toggle_obj",
            "sprite_path": "",
            "sprite_shape": "rectangle",
            "sprite_color": [
                255,
                165,
                255
            ],
            "transform": {
                "x": 650.0,
                "y": 120.0,
                "rotation": 0.0,
                "scale_x": 1.0,
                "scale_y": 1.0
            },
            "z_index": 0,
            "screen_space": false,
            "active": true,
            "locked": false,
            "physics_type": "none",
            "physics_mass": 1.0,
            "physics_friction": 0.98,
            "physics_bounce": 0.5,
            "physics_collision_category": null,
            "physics_collision_mask": null,
            "custom_data": {
                "width": 100,
                "height": 40
            }
        },
        {
            "id": "14ad5bab",
            "name": "button",
            "sprite_path": "",
            "sprite_shape": "rectangle",
            "sprite_color": [
                210,
                210,
                210
            ],
            "transform": {
                "x": 140.0,
                "y": 120.0,
                "rotation": 0.0,
                "scale_x": 1.0,
                "scale_y": 1.0
            },
            "z_index": 1000,
            "screen_space": false,
            "active": true,
            "locked": false,
            "physics_type": "none",
            "physics_mass": 1.0,
            "physics_friction": 0.98,
            "physics_bounce": 0.5,
            "physics_collision_category": null,
            "physics_collision_mask": null,
            "custom_data": {
                "width": 170,
                "height": 50
            }
        },
        {
            "id": "eed14b69",
            "name": "hint",
            "sprite_path": "",
            "sprite_shape": "rectangle",
            "sprite_color": [
                200,
                200,
                200
            ],
            "transform": {
                "x": 400.0,
                "y": 540.0,
                "rotation": 0.0,
                "scale_x": 1.0,
                "scale_y": 1.0
            },
            "z_index": 1000,
            "screen_space": false,
            "active": true,
            "locked": false,
            "physics_type": "none",
            "physics_mass": 1.0,
            "physics_friction": 0.98,
            "physics_bounce": 0.5,
            "physics_collision_category": null,
            "physics_collision_mask": null,
            "custom_data": {
                "width": 525,
                "height": 16
            }
        },
        {
            "id": "84938b6a",
            "name": "label",
            "sprite_path": "",
            "sprite_shape": "rectangle",
            "sprite_color": [
                255,
                255,
                255
            ],
            "transform": {
                "x": 400.0,
                "y": 300.0,
                "rotation": 0.0,
                "scale_x": 1.0,
                "scale_y": 1.0
            },
            "z_index": 1000,
            "screen_space": false,
            "active": true,
            "locked": false,
            "physics_type": "none",
            "physics_mass": 1.0,
            "physics_friction": 0.98,
            "physics_bounce": 0.5,
            "physics_collision_category": null,
            "physics_collision_mask": null,
            "custom_data": {
                "width": 232,
                "height": 22
            }
        },
        {
            "id": "c34083b8",
            "name": "timer_label",
            "sprite_path": "",
            "sprite_shape": "rectangle",
            "sprite_color": [
                220,
                220,
                220
            ],
            "transform": {
                "x": 165.0,
                "y": 246.0,
                "rotation": 0.0,
                "scale_x": 1.0,
                "scale_y": 1.0
            },
            "z_index": 1000,
            "screen_space": false,
            "active": true,
            "locked": false,
            "physics_type": "none",
            "physics_mass": 1.0,
            "physics_friction": 0.98,
            "physics_bounce": 0.5,
            "physics_collision_category": null,
            "physics_collision_mask": null,
            "custom_data": {
                "width": 51,
                "height": 13
            }
        },
        {
            "id": "92ce3cf6",
            "name": "toggle",
            "sprite_path": "",
            "sprite_shape": "rectangle",
            "sprite_color": [
                80,
                180,
                120
            ],
            "transform": {
                "x": 140.0,
                "y": 180.0,
                "rotation": 0.0,
                "scale_x": 1.0,
                "scale_y": 1.0
            },
            "z_index": 1000,
            "screen_space": false,
            "active": true,
            "locked": false,
            "physics_type": "none",
            "physics_mass": 1.0,
            "physics_friction": 0.98,
            "physics_bounce": 0.5,
            "physics_collision_category": null,
            "physics_collision_mask": null,
            "custom_data": {
                "width": 170,
                "height": 50
            }
        }
    ],
    "grid_size": 10,
    "grid_visible": true,
    "grid_labels_visible": true,
    "snap_to_grid": true
}